entrezpy/__init__.py
entrezpy/conduit.py
entrezpy/base/__init__.py
entrezpy/base/analyzer.py
entrezpy/base/parameter.py
entrezpy/base/query.py
entrezpy/base/referencer.py
entrezpy/base/request.py
entrezpy/base/result.py
entrezpy/efetch/__init__.py
entrezpy/efetch/efetch_analyzer.py
entrezpy/efetch/efetch_parameter.py
entrezpy/efetch/efetch_request.py
entrezpy/efetch/efetcher.py
entrezpy/elink/__init__.py
entrezpy/elink/elink_analyzer.py
entrezpy/elink/elink_parameter.py
entrezpy/elink/elink_request.py
entrezpy/elink/elink_result.py
entrezpy/elink/elinker.py
entrezpy/elink/linkset/__init__.py
entrezpy/elink/linkset/base.py
entrezpy/elink/linkset/linked.py
entrezpy/elink/linkset/relaxed.py
entrezpy/elink/linkset/unit/__init__.py
entrezpy/elink/linkset/unit/linkin.py
entrezpy/elink/linkset/unit/linklist.py
entrezpy/elink/linkset/unit/linkout.py
entrezpy/elink/linkset/unit/linkoutallattribute.py
entrezpy/elink/linkset/unit/linkoutnonlibattribute.py
entrezpy/elink/linkset/unit/linkoutprovider.py
entrezpy/elink/linkset/unit/linksetunit.py
entrezpy/elink/linkset/unit/neighbor.py
entrezpy/elink/linkset/unit/neighborhistory.py
entrezpy/elink/linkset/unit/neighborscore.py
entrezpy/epost/__init__.py
entrezpy/epost/epost_analyzer.py
entrezpy/epost/epost_parameter.py
entrezpy/epost/epost_request.py
entrezpy/epost/epost_result.py
entrezpy/epost/eposter.py
entrezpy/esearch/__init__.py
entrezpy/esearch/esearch_analyzer.py
entrezpy/esearch/esearch_parameter.py
entrezpy/esearch/esearch_request.py
entrezpy/esearch/esearch_result.py
entrezpy/esearch/esearcher.py
entrezpy/esummary/__init__.py
entrezpy/esummary/esummarizer.py
entrezpy/esummary/esummary_analyzer.py
entrezpy/esummary/esummary_parameter.py
entrezpy/esummary/esummary_request.py
entrezpy/esummary/esummary_result.py
entrezpy/log/__init__.py
entrezpy/log/conf.py
entrezpy/log/logger.py
entrezpy/requester/__init__.py
entrezpy/requester/monitor.py
entrezpy/requester/requester.py
entrezpy/requester/requestpool.py
entrezpy-2.1.3.dist-info/LICENSE
entrezpy-2.1.3.dist-info/METADATA
entrezpy-2.1.3.dist-info/WHEEL
entrezpy-2.1.3.dist-info/top_level.txt
entrezpy-2.1.3.dist-info/RECORD
